fluo/__init__.py
fluo/apps.py
fluo/context_processors.py
fluo/http.py
fluo/settings.py
fluo/shortcuts.py
fluo/urls.py
fluo/admin/__init__.py
fluo/admin/base.py
fluo/admin/models.py
fluo/admin/nested.py
fluo/admin/sites.py
fluo/admin/views.py
fluo/admin/widgets.py
fluo/db/__init__.py
fluo/db/backend.py
fluo/db/backends/__init__.py
fluo/db/backends/dummy.py
fluo/db/backends/mysql.py
fluo/db/backends/oracle.py
fluo/db/backends/postgis.py
fluo/db/backends/postgresql.py
fluo/db/backends/spatialite.py
fluo/db/backends/sqlite3.py
fluo/db/models/__init__.py
fluo/db/models/enums.py
fluo/db/models/fields.py
fluo/db/models/models.py
fluo/db/models/postgresql.py
fluo/forms/__init__.py
fluo/forms/fields.py
fluo/forms/widgets.py
fluo/locale/en/LC_MESSAGES/django.mo
fluo/locale/en/LC_MESSAGES/django.po
fluo/locale/it/LC_MESSAGES/django.mo
fluo/locale/it/LC_MESSAGES/django.po
fluo/management/__init__.py
fluo/management/database.py
fluo/management/mixins.py
fluo/management/commands/__init__.py
fluo/management/commands/compilemessages.py
fluo/management/commands/createdb.py
fluo/management/commands/devdb.py
fluo/management/commands/dropdb.py
fluo/management/commands/initdb.py
fluo/management/commands/load_admin_data.py
fluo/management/commands/makemessages.py
fluo/management/commands/passwd.py
fluo/management/commands/pip.py
fluo/middleware/__init__.py
fluo/middleware/debug.py
fluo/middleware/locale.py
fluo/static/fluo/admin/css/forms-nested.css
fluo/static/fluo/admin/js/inlines-nested.js
fluo/static/fluo/admin/js/inlines-nested.min.js
fluo/static/fluo/flags/de.gif
fluo/static/fluo/flags/en.gif
fluo/static/fluo/flags/es.gif
fluo/static/fluo/flags/fr.gif
fluo/static/fluo/flags/it.gif
fluo/templates/admin/base_site.html
fluo/templates/admin/custom_site.html
fluo/templates/admin/filter.html
fluo/templates/admin/languages.html
fluo/templates/admin/edit_inline/stacked-nested.html
fluo/templates/admin/edit_inline/tabular-nested.html
fluo/templates/fluo/tags/content.html
django_fluo-0.5.dist-info/AUTHORS
django_fluo-0.5.dist-info/COPYING
django_fluo-0.5.dist-info/METADATA
django_fluo-0.5.dist-info/WHEEL
django_fluo-0.5.dist-info/top_level.txt
django_fluo-0.5.dist-info/RECORD
