Metadata-Version: 2.1
Name: django-fluo
Version: 0.5
Summary: various django utilities
Home-page: https://pypi.org/project/django-fluo/
Author: Raffaele Salmaso
Author-email: raffaele@salmaso.org
License: MIT
Project-URL: GitHub, https://github.com/rsalmaso/django-fluo
Project-URL: GitLab, https://gitlab.com/rsalmaso/django-fluo
Platform: any
Classifier: Operating System :: OS Independent
Classifier: Programming Language :: Python
Classifier: Topic :: Internet :: WWW/HTTP
Classifier: Topic :: Internet :: WWW/HTTP :: Dynamic Content
Classifier: Topic :: Internet :: WWW/HTTP :: WSGI
Classifier: Topic :: Software Development :: Libraries :: Application Frameworks
Classifier: Topic :: Software Development :: Libraries :: Python Modules
Classifier: Framework :: Django
Classifier: Framework :: Django :: 3.2
Classifier: Framework :: Django :: 4.0
Classifier: Framework :: Django :: 4.1
Classifier: License :: OSI Approved :: MIT License
Classifier: Programming Language :: Python :: 3
Classifier: Programming Language :: Python :: 3.8
Classifier: Programming Language :: Python :: 3.9
Classifier: Programming Language :: Python :: 3.10
Classifier: Programming Language :: Python :: 3.11
Requires-Python: >=3.8
License-File: COPYING
License-File: AUTHORS
Requires-Dist: django
